iportfolio/__init__.py
iportfolio/admin.py
iportfolio/apps.py
iportfolio/models.py
iportfolio/tests.py
iportfolio/urls.py
iportfolio/views.py
iportfolio/static/iportfolio/css/style.css
iportfolio/static/iportfolio/img/apple-touch-icon.png
iportfolio/static/iportfolio/img/favicon.png
iportfolio/static/iportfolio/img/hero-bg.jpg
iportfolio/static/iportfolio/img/profile-img.jpg
iportfolio/static/iportfolio/img/portfolio/portfolio-1.jpg
iportfolio/static/iportfolio/img/portfolio/portfolio-2.jpg
iportfolio/static/iportfolio/img/portfolio/portfolio-3.jpg
iportfolio/static/iportfolio/img/portfolio/portfolio-4.jpg
iportfolio/static/iportfolio/img/portfolio/portfolio-5.jpg
iportfolio/static/iportfolio/img/portfolio/portfolio-6.jpg
iportfolio/static/iportfolio/img/portfolio/portfolio-7.jpg
iportfolio/static/iportfolio/img/portfolio/portfolio-8.jpg
iportfolio/static/iportfolio/img/portfolio/portfolio-9.jpg
iportfolio/static/iportfolio/img/portfolio/portfolio-details-1.jpg
iportfolio/static/iportfolio/img/portfolio/portfolio-details-2.jpg
iportfolio/static/iportfolio/img/portfolio/portfolio-details-3.jpg
iportfolio/static/iportfolio/img/testimonials/testimonials-1.jpg
iportfolio/static/iportfolio/img/testimonials/testimonials-2.jpg
iportfolio/static/iportfolio/img/testimonials/testimonials-3.jpg
iportfolio/static/iportfolio/img/testimonials/testimonials-4.jpg
iportfolio/static/iportfolio/img/testimonials/testimonials-5.jpg
iportfolio/static/iportfolio/js/main.js
iportfolio/static/iportfolio/scss/_footer.scss
iportfolio/static/iportfolio/scss/_general.scss
iportfolio/static/iportfolio/scss/_header.scss
iportfolio/static/iportfolio/scss/_hero.scss
iportfolio/static/iportfolio/scss/_nav.scss
iportfolio/static/iportfolio/scss/_sections.scss
iportfolio/static/iportfolio/scss/_variables.scss
iportfolio/static/iportfolio/scss/style.scss
iportfolio/static/iportfolio/vendor/aos/aos.css
iportfolio/static/iportfolio/vendor/aos/aos.js
django_iportfolio_ds-0.0.6.dist-info/LICENSE
django_iportfolio_ds-0.0.6.dist-info/METADATA
django_iportfolio_ds-0.0.6.dist-info/WHEEL
django_iportfolio_ds-0.0.6.dist-info/top_level.txt
django_iportfolio_ds-0.0.6.dist-info/RECORD
