Metadata-Version: 2.1
Name: django-iportfolio-ds
Version: 0.0.6
Summary: iportfolio_pro porting for django
Home-page: https://www.demiansoft.com
Author: hyungjin kim
Author-email: hj3415@gmail.com
Project-URL: Bug Tracker, https://pypi.org/project/util-demian/
Classifier: License :: OSI Approved :: BSD License
Classifier: Operating System :: OS Independent
Classifier: Programming Language :: Python :: 3
Requires-Python: >=3.8
License-File: LICENSE
Requires-Dist: Django (>=4.0.6)
Requires-Dist: util-demian (>=0.0.4)
Requires-Dist: django-demian-parts (>=0.3.2)
Requires-Dist: django-compressor (>=4.0)
Requires-Dist: django-libsass (>=0.9)
